daalab/__init__.py
daalab/codes.py
daalab/testing.py
daalab-1.5.dist-info/METADATA
daalab-1.5.dist-info/WHEEL
daalab-1.5.dist-info/top_level.txt
daalab-1.5.dist-info/RECORD
