Metadata-Version: 2.1
Name: daalab
Version: 1.5
Summary: A Python library for all daa lab questions
Author: Imad
Author-email: mdimad005@gmail.com
